{
  "type": "minecraft:generic",
  "pools": [
    {
      "rolls": 1,
      "entries": [
        {
          "type": "minecraft:item",
          "name": "minecraft:written_book",
          "functions": [
            {
              "function": "minecraft:set_components",
              "components": {
                "minecraft:custom_name": {
                  "text": "The First Map",
                  "color": "green",
                  "italic": false
                },
                "minecraft:lore": [
                  {
                    "text": "The Wanderer's Oath",
                    "color": "gray",
                    "italic": false
                  },
                  {
                    "text": "Uncommon Lore Fragment",
                    "color": "white",
                    "italic": false
                  },
                  "",
                  {
                    "text": "[Right-click to read]",
                    "color": "yellow",
                    "italic": true
                  }
                ],
                "minecraft:written_book_content": {
                  "title": "The First Map",
                  "author": "Expeditionist",
                  "pages": [
                    [
                      {
                        "text": "My first map was wrong in every detail. But it was mine, and it led me to places no correct map ever could.",
                        "color": "dark_gray",
                        "italic": true
                      }
                    ],
                    [
                      {
                        "text": "\n\n  ",
                        "color": "white"
                      },
                      {
                        "text": "[Add to Collection]",
                        "color": "green",
                        "bold": true,
                        "click_event": {
                          "action": "run_command",
                          "command": "/trigger ec.lore_add set 15402"
                        }
                      }
                    ]
                  ]
                },
                "minecraft:custom_data": {
                  "lore_piece": true,
                  "lore_uid": 15402,
                  "lore_set": 154,
                  "lore_pid": 2
                },
                "minecraft:enchantment_glint_override": true
              }
            }
          ]
        }
      ]
    }
  ]
}
