{
  "type": "minecraft:generic",
  "pools": [
    {
      "rolls": 1,
      "entries": [
        {
          "type": "minecraft:item",
          "name": "minecraft:written_book",
          "functions": [
            {
              "function": "minecraft:set_components",
              "components": {
                "minecraft:custom_name": {
                  "text": "Furia's Question",
                  "color": "light_purple",
                  "italic": false
                },
                "minecraft:lore": [
                  {
                    "text": "Furia Genesis",
                    "color": "gray",
                    "italic": false
                  },
                  {
                    "text": "Ornate Lore Fragment",
                    "color": "white",
                    "italic": false
                  },
                  "",
                  {
                    "text": "[Right-click to read]",
                    "color": "yellow",
                    "italic": true
                  }
                ],
                "minecraft:written_book_content": {
                  "title": "Furia's Question",
                  "author": "Shadow Chronicler",
                  "pages": [
                    [
                      {
                        "text": "Every Furia asks the same question: 'Why bother?' The answer \u2014 the only answer that destroys them \u2014 is to bother anyway.",
                        "color": "dark_gray",
                        "italic": true
                      }
                    ],
                    [
                      {
                        "text": "The most potent weapon against a Furia is not a sword or spell. It is a child's drawing, pinned to a wall. It is a garden, tended through winter. It is any act of stubborn, beautiful creation.",
                        "color": "dark_gray",
                        "italic": true
                      }
                    ],
                    [
                      {
                        "text": "\n\n  ",
                        "color": "white"
                      },
                      {
                        "text": "[Add to Collection]",
                        "color": "green",
                        "bold": true,
                        "click_event": {
                          "action": "run_command",
                          "command": "/trigger ec.lore_add set 14205"
                        }
                      }
                    ]
                  ]
                },
                "minecraft:custom_data": {
                  "lore_piece": true,
                  "lore_uid": 14205,
                  "lore_set": 142,
                  "lore_pid": 5
                },
                "minecraft:enchantment_glint_override": true
              }
            }
          ]
        }
      ]
    }
  ]
}
