{
  "type": "minecraft:generic",
  "pools": [
    {
      "rolls": {
        "type": "minecraft:uniform",
        "min": 4,
        "max": 6
      },
      "comment": "VALUABLES POOL - Premium materials, netherite appears",
      "entries": [
        {
          "type": "minecraft:empty",
          "weight": 5
        },
        {
          "type": "minecraft:item",
          "name": "minecraft:diamond_block",
          "weight": 15,
          "functions": [
            {
              "function": "minecraft:set_count",
              "count": {
                "min": 1,
                "max": 3
              }
            }
          ]
        },
        {
          "type": "minecraft:item",
          "name": "minecraft:netherite_ingot",
          "weight": 5,
          "conditions": [
            {
              "condition": "minecraft:random_chance",
              "chance": 0.05
            }
          ]
        },
        {
          "type": "minecraft:item",
          "name": "minecraft:gold_block",
          "weight": 12,
          "functions": [
            {
              "function": "minecraft:set_count",
              "count": {
                "min": 2,
                "max": 4
              }
            }
          ]
        },
        {
          "type": "minecraft:item",
          "name": "minecraft:iron_block",
          "weight": 10,
          "functions": [
            {
              "function": "minecraft:set_count",
              "count": {
                "min": 3,
                "max": 6
              }
            }
          ]
        },
        {
          "type": "minecraft:item",
          "name": "minecraft:emerald_block",
          "weight": 12,
          "functions": [
            {
              "function": "minecraft:set_count",
              "count": {
                "min": 1,
                "max": 3
              }
            }
          ]
        },
        {
          "type": "minecraft:item",
          "name": "minecraft:diamond",
          "weight": 20,
          "functions": [
            {
              "function": "minecraft:set_count",
              "count": {
                "min": 4,
                "max": 8
              }
            }
          ]
        },
        {
          "type": "minecraft:item",
          "name": "minecraft:echo_shard",
          "weight": 8,
          "functions": [
            {
              "function": "minecraft:set_count",
              "count": {
                "min": 2,
                "max": 5
              }
            }
          ]
        },
        {
          "type": "minecraft:item",
          "name": "minecraft:amethyst_block",
          "weight": 8,
          "functions": [
            {
              "function": "minecraft:set_count",
              "count": {
                "min": 2,
                "max": 4
              }
            }
          ]
        },
        {
          "type": "minecraft:item",
          "name": "minecraft:nether_star",
          "weight": 5,
          "conditions": [
            {
              "condition": "minecraft:random_chance",
              "chance": 0.2
            }
          ]
        }
      ]
    },
    {
      "rolls": 1,
      "comment": "ANCIENT DEBRIS POOL - 15-25% chance scaled by luck",
      "entries": [
        {
          "type": "minecraft:empty",
          "weight": 85
        },
        {
          "type": "minecraft:item",
          "name": "minecraft:ancient_debris",
          "weight": 15,
          "functions": [
            {
              "function": "minecraft:set_count",
              "count": {
                "min": 2,
                "max": 4
              }
            }
          ],
          "quality": 10
        }
      ]
    },
    {
      "rolls": {
        "type": "minecraft:uniform",
        "min": 1,
        "max": 2
      },
      "comment": "CONSUMABLES POOL - Best consumables",
      "entries": [
        {
          "type": "minecraft:empty",
          "weight": 15
        },
        {
          "type": "minecraft:item",
          "name": "minecraft:golden_apple",
          "weight": 20,
          "functions": [
            {
              "function": "minecraft:set_count",
              "count": {
                "min": 3,
                "max": 6
              }
            }
          ]
        },
        {
          "type": "minecraft:item",
          "name": "minecraft:enchanted_golden_apple",
          "weight": 10,
          "functions": [
            {
              "function": "minecraft:set_count",
              "count": {
                "min": 1,
                "max": 2
              }
            }
          ]
        },
        {
          "type": "minecraft:item",
          "name": "minecraft:totem_of_undying",
          "weight": 15,
          "comment": "B5 BALANCE: Max 1 totem per chest normally"
        },
        {
          "type": "minecraft:item",
          "name": "minecraft:experience_bottle",
          "weight": 20,
          "functions": [
            {
              "function": "minecraft:set_count",
              "count": {
                "min": 12,
                "max": 24
              }
            }
          ]
        },
        {
          "type": "minecraft:item",
          "name": "minecraft:ender_pearl",
          "weight": 20,
          "functions": [
            {
              "function": "minecraft:set_count",
              "count": {
                "min": 8,
                "max": 16
              }
            }
          ]
        }
      ]
    },
    {
      "rolls": 1,
      "comment": "MOB DROPS POOL - Exotic drops",
      "entries": [
        {
          "type": "minecraft:empty",
          "weight": 25
        },
        {
          "type": "minecraft:item",
          "name": "minecraft:blaze_rod",
          "weight": 15,
          "functions": [
            {
              "function": "minecraft:set_count",
              "count": {
                "min": 6,
                "max": 12
              }
            }
          ]
        },
        {
          "type": "minecraft:item",
          "name": "minecraft:ghast_tear",
          "weight": 12,
          "functions": [
            {
              "function": "minecraft:set_count",
              "count": {
                "min": 3,
                "max": 6
              }
            }
          ]
        },
        {
          "type": "minecraft:item",
          "name": "minecraft:shulker_shell",
          "weight": 10,
          "functions": [
            {
              "function": "minecraft:set_count",
              "count": 2
            }
          ]
        },
        {
          "type": "minecraft:item",
          "name": "minecraft:wither_skeleton_skull",
          "weight": 8,
          "conditions": [
            {
              "condition": "minecraft:random_chance",
              "chance": 0.35
            }
          ]
        },
        {
          "type": "minecraft:item",
          "name": "minecraft:ender_eye",
          "weight": 15,
          "functions": [
            {
              "function": "minecraft:set_count",
              "count": {
                "min": 4,
                "max": 8
              }
            }
          ]
        },
        {
          "type": "minecraft:item",
          "name": "minecraft:heart_of_the_sea",
          "weight": 8
        },
        {
          "type": "minecraft:item",
          "name": "minecraft:dragon_breath",
          "weight": 7,
          "functions": [
            {
              "function": "minecraft:set_count",
              "count": {
                "min": 2,
                "max": 4
              }
            }
          ]
        }
      ]
    },
    {
      "rolls": 1,
      "comment": "UTILITY POOL - Best utility items",
      "entries": [
        {
          "type": "minecraft:empty",
          "weight": 35
        },
        {
          "type": "minecraft:item",
          "name": "minecraft:shulker_box",
          "weight": 10
        },
        {
          "type": "minecraft:item",
          "name": "minecraft:ender_chest",
          "weight": 8
        },
        {
          "type": "minecraft:item",
          "name": "minecraft:recovery_compass",
          "weight": 10
        },
        {
          "type": "minecraft:item",
          "name": "minecraft:goat_horn",
          "weight": 10,
          "functions": [
            {
              "function": "minecraft:set_instrument",
              "options": "#minecraft:goat_horns"
            }
          ]
        },
        {
          "type": "minecraft:item",
          "name": "minecraft:lodestone",
          "weight": 5
        },
        {
          "type": "minecraft:item",
          "name": "minecraft:respawn_anchor",
          "weight": 7
        },
        {
          "type": "minecraft:item",
          "name": "minecraft:beacon",
          "weight": 3,
          "conditions": [
            {
              "condition": "minecraft:random_chance",
              "chance": 0.1
            }
          ]
        },
        {
          "type": "minecraft:item",
          "name": "minecraft:tipped_arrow",
          "weight": 12,
          "functions": [
            {
              "function": "minecraft:set_count",
              "count": {
                "min": 16,
                "max": 32
              }
            },
            {
              "function": "minecraft:set_potion",
              "id": "minecraft:strong_harming"
            }
          ]
        }
      ]
    },
    {
      "rolls": {
        "type": "minecraft:uniform",
        "min": 0,
        "max": 2
      },
      "comment": "ARMOR POOL - Diamond/Netherite, tiered quality",
      "entries": [
        {
          "type": "minecraft:empty",
          "weight": 40
        },
        {
          "type": "minecraft:item",
          "name": "minecraft:diamond_helmet",
          "weight": 10,
          "functions": [
            {
              "function": "minecraft:enchant_with_levels",
              "levels": 40,
              "options": "#minecraft:on_random_loot"
            }
          ]
        },
        {
          "type": "minecraft:item",
          "name": "minecraft:diamond_chestplate",
          "weight": 8,
          "functions": [
            {
              "function": "minecraft:enchant_with_levels",
              "levels": 40,
              "options": "#minecraft:on_random_loot"
            }
          ]
        },
        {
          "type": "minecraft:item",
          "name": "minecraft:diamond_leggings",
          "weight": 8,
          "functions": [
            {
              "function": "minecraft:enchant_with_levels",
              "levels": 40,
              "options": "#minecraft:on_random_loot"
            }
          ]
        },
        {
          "type": "minecraft:item",
          "name": "minecraft:diamond_boots",
          "weight": 8,
          "functions": [
            {
              "function": "minecraft:enchant_with_levels",
              "levels": 40,
              "options": "#minecraft:on_random_loot"
            }
          ]
        },
        {
          "type": "minecraft:item",
          "name": "minecraft:netherite_helmet",
          "weight": 6,
          "functions": [
            {
              "function": "minecraft:enchant_with_levels",
              "levels": {
                "min": 35,
                "max": 50
              },
              "options": "#minecraft:on_random_loot",
              "conditions": [
                {
                  "condition": "minecraft:random_chance",
                  "chance": 0.75
                }
              ]
            }
          ]
        },
        {
          "type": "minecraft:item",
          "name": "minecraft:netherite_chestplate",
          "weight": 5,
          "functions": [
            {
              "function": "minecraft:enchant_with_levels",
              "levels": {
                "min": 35,
                "max": 50
              },
              "options": "#minecraft:on_random_loot",
              "conditions": [
                {
                  "condition": "minecraft:random_chance",
                  "chance": 0.75
                }
              ]
            }
          ]
        },
        {
          "type": "minecraft:item",
          "name": "minecraft:netherite_leggings",
          "weight": 5,
          "functions": [
            {
              "function": "minecraft:enchant_with_levels",
              "levels": {
                "min": 35,
                "max": 50
              },
              "options": "#minecraft:on_random_loot",
              "conditions": [
                {
                  "condition": "minecraft:random_chance",
                  "chance": 0.75
                }
              ]
            }
          ]
        },
        {
          "type": "minecraft:item",
          "name": "minecraft:netherite_boots",
          "weight": 5,
          "functions": [
            {
              "function": "minecraft:enchant_with_levels",
              "levels": {
                "min": 35,
                "max": 50
              },
              "options": "#minecraft:on_random_loot",
              "conditions": [
                {
                  "condition": "minecraft:random_chance",
                  "chance": 0.75
                }
              ]
            }
          ]
        },
        {
          "type": "minecraft:item",
          "name": "minecraft:elytra",
          "weight": 5,
          "conditions": [
            {
              "condition": "minecraft:random_chance",
              "chance": 0.15
            }
          ],
          "functions": [
            {
              "function": "minecraft:set_damage",
              "damage": {
                "min": 0.5,
                "max": 0.9
              }
            }
          ]
        }
      ]
    },
    {
      "rolls": 1,
      "comment": "WEAPON POOL - Best weapons including rare mace/trident",
      "entries": [
        {
          "type": "minecraft:empty",
          "weight": 45
        },
        {
          "type": "minecraft:item",
          "name": "minecraft:diamond_sword",
          "weight": 10,
          "functions": [
            {
              "function": "minecraft:enchant_with_levels",
              "levels": 45,
              "options": "#minecraft:on_random_loot"
            }
          ]
        },
        {
          "type": "minecraft:item",
          "name": "minecraft:netherite_sword",
          "weight": 12,
          "functions": [
            {
              "function": "minecraft:enchant_with_levels",
              "levels": {
                "min": 35,
                "max": 50
              },
              "options": "#minecraft:on_random_loot",
              "conditions": [
                {
                  "condition": "minecraft:random_chance",
                  "chance": 0.75
                }
              ]
            }
          ]
        },
        {
          "type": "minecraft:item",
          "name": "minecraft:netherite_axe",
          "weight": 8,
          "functions": [
            {
              "function": "minecraft:enchant_with_levels",
              "levels": {
                "min": 35,
                "max": 50
              },
              "options": "#minecraft:on_random_loot",
              "conditions": [
                {
                  "condition": "minecraft:random_chance",
                  "chance": 0.75
                }
              ]
            }
          ]
        },
        {
          "type": "minecraft:item",
          "name": "minecraft:bow",
          "weight": 8,
          "functions": [
            {
              "function": "minecraft:enchant_with_levels",
              "levels": 40,
              "options": "#minecraft:on_random_loot"
            }
          ]
        },
        {
          "type": "minecraft:item",
          "name": "minecraft:crossbow",
          "weight": 6,
          "functions": [
            {
              "function": "minecraft:enchant_with_levels",
              "levels": 38,
              "options": "#minecraft:on_random_loot"
            }
          ]
        },
        {
          "type": "minecraft:item",
          "name": "minecraft:trident",
          "weight": 6,
          "functions": [
            {
              "function": "minecraft:set_damage",
              "damage": {
                "min": 0.7,
                "max": 1.0
              }
            },
            {
              "function": "minecraft:enchant_with_levels",
              "levels": 35,
              "options": "#minecraft:on_random_loot"
            }
          ]
        }
      ]
    },
    {
      "rolls": 1,
      "comment": "MACE POOL - 1% chance for mace (Mythical gets better enchants)",
      "entries": [
        {
          "type": "minecraft:empty",
          "weight": 99
        },
        {
          "type": "minecraft:item",
          "weight": 1,
          "name": "minecraft:mace",
          "functions": [
            {
              "function": "minecraft:enchant_with_levels",
              "levels": {
                "min": 35,
                "max": 50
              },
              "options": "#minecraft:on_random_loot"
            }
          ]
        }
      ]
    },
    {
      "rolls": 1,
      "comment": "TOOL POOL - Best tools",
      "entries": [
        {
          "type": "minecraft:empty",
          "weight": 40
        },
        {
          "type": "minecraft:item",
          "name": "minecraft:diamond_pickaxe",
          "weight": 12,
          "functions": [
            {
              "function": "minecraft:enchant_with_levels",
              "levels": 45,
              "options": "#minecraft:on_random_loot"
            }
          ]
        },
        {
          "type": "minecraft:item",
          "name": "minecraft:netherite_pickaxe",
          "weight": 15,
          "functions": [
            {
              "function": "minecraft:enchant_with_levels",
              "levels": {
                "min": 35,
                "max": 50
              },
              "options": "#minecraft:on_random_loot",
              "conditions": [
                {
                  "condition": "minecraft:random_chance",
                  "chance": 0.75
                }
              ]
            }
          ]
        },
        {
          "type": "minecraft:item",
          "name": "minecraft:netherite_shovel",
          "weight": 10,
          "functions": [
            {
              "function": "minecraft:enchant_with_levels",
              "levels": {
                "min": 30,
                "max": 45
              },
              "options": "#minecraft:on_random_loot",
              "conditions": [
                {
                  "condition": "minecraft:random_chance",
                  "chance": 0.7
                }
              ]
            }
          ]
        },
        {
          "type": "minecraft:item",
          "name": "minecraft:netherite_hoe",
          "weight": 8,
          "functions": [
            {
              "function": "minecraft:enchant_with_levels",
              "levels": 35,
              "options": "#minecraft:on_random_loot"
            }
          ]
        },
        {
          "type": "minecraft:item",
          "name": "minecraft:fishing_rod",
          "weight": 8,
          "functions": [
            {
              "function": "minecraft:enchant_with_levels",
              "levels": 35,
              "options": "#minecraft:on_random_loot"
            }
          ]
        },
        {
          "type": "minecraft:item",
          "name": "minecraft:shield",
          "weight": 7,
          "functions": [
            {
              "function": "minecraft:enchant_with_levels",
              "levels": 35,
              "options": "#minecraft:on_random_loot"
            }
          ]
        }
      ]
    },
    {
      "rolls": 1,
      "comment": "PET POOL 1 - 30% chance",
      "entries": [
        {
          "type": "minecraft:empty",
          "weight": 93
        },
        {
          "type": "minecraft:loot_table",
          "value": "evercraft:pets/biome/mythical_0",
          "conditions": [
            {
              "condition": "minecraft:location_check",
              "predicate": {
                "biomes": [
                  "minecraft:plains",
                  "minecraft:sunflower_plains",
                  "minecraft:meadow"
                ]
              }
            }
          ],
          "weight": 7
        },
        {
          "type": "minecraft:loot_table",
          "value": "evercraft:pets/biome/mythical_1",
          "conditions": [
            {
              "condition": "minecraft:location_check",
              "predicate": {
                "biomes": [
                  "minecraft:forest",
                  "minecraft:birch_forest",
                  "minecraft:old_growth_birch_forest"
                ]
              }
            }
          ],
          "weight": 7
        },
        {
          "type": "minecraft:loot_table",
          "value": "evercraft:pets/biome/mythical_2",
          "conditions": [
            {
              "condition": "minecraft:location_check",
              "predicate": {
                "biomes": [
                  "minecraft:flower_forest",
                  "minecraft:cherry_grove"
                ]
              }
            }
          ],
          "weight": 7
        },
        {
          "type": "minecraft:loot_table",
          "value": "evercraft:pets/biome/mythical_3",
          "conditions": [
            {
              "condition": "minecraft:location_check",
              "predicate": {
                "biomes": [
                  "minecraft:dark_forest",
                  "minecraft:pale_garden"
                ]
              }
            }
          ],
          "weight": 7
        },
        {
          "type": "minecraft:loot_table",
          "value": "evercraft:pets/biome/mythical_4",
          "conditions": [
            {
              "condition": "minecraft:location_check",
              "predicate": {
                "biomes": [
                  "minecraft:taiga",
                  "minecraft:old_growth_pine_taiga",
                  "minecraft:old_growth_spruce_taiga",
                  "minecraft:snowy_taiga"
                ]
              }
            }
          ],
          "weight": 7
        },
        {
          "type": "minecraft:loot_table",
          "value": "evercraft:pets/biome/mythical_5",
          "conditions": [
            {
              "condition": "minecraft:location_check",
              "predicate": {
                "biomes": [
                  "minecraft:windswept_hills",
                  "minecraft:windswept_gravelly_hills",
                  "minecraft:windswept_forest",
                  "minecraft:stony_peaks",
                  "minecraft:jagged_peaks",
                  "minecraft:frozen_peaks",
                  "minecraft:grove",
                  "minecraft:snowy_slopes"
                ]
              }
            }
          ],
          "weight": 7
        },
        {
          "type": "minecraft:loot_table",
          "value": "evercraft:pets/biome/mythical_6",
          "conditions": [
            {
              "condition": "minecraft:location_check",
              "predicate": {
                "biomes": [
                  "minecraft:jungle",
                  "minecraft:sparse_jungle",
                  "minecraft:bamboo_jungle"
                ]
              }
            }
          ],
          "weight": 7
        },
        {
          "type": "minecraft:loot_table",
          "value": "evercraft:pets/biome/mythical_7",
          "conditions": [
            {
              "condition": "minecraft:location_check",
              "predicate": {
                "biomes": "minecraft:desert"
              }
            }
          ],
          "weight": 7
        },
        {
          "type": "minecraft:loot_table",
          "value": "evercraft:pets/biome/mythical_8",
          "conditions": [
            {
              "condition": "minecraft:location_check",
              "predicate": {
                "biomes": [
                  "minecraft:savanna",
                  "minecraft:savanna_plateau",
                  "minecraft:windswept_savanna"
                ]
              }
            }
          ],
          "weight": 7
        },
        {
          "type": "minecraft:loot_table",
          "value": "evercraft:pets/biome/mythical_9",
          "conditions": [
            {
              "condition": "minecraft:location_check",
              "predicate": {
                "biomes": [
                  "minecraft:ocean",
                  "minecraft:deep_ocean",
                  "minecraft:warm_ocean",
                  "minecraft:lukewarm_ocean",
                  "minecraft:deep_lukewarm_ocean",
                  "minecraft:cold_ocean",
                  "minecraft:deep_cold_ocean",
                  "minecraft:frozen_ocean",
                  "minecraft:deep_frozen_ocean"
                ]
              }
            }
          ],
          "weight": 7
        },
        {
          "type": "minecraft:loot_table",
          "value": "evercraft:pets/biome/mythical_10",
          "conditions": [
            {
              "condition": "minecraft:location_check",
              "predicate": {
                "biomes": [
                  "minecraft:river",
                  "minecraft:frozen_river"
                ]
              }
            }
          ],
          "weight": 7
        },
        {
          "type": "minecraft:loot_table",
          "value": "evercraft:pets/biome/mythical_11",
          "conditions": [
            {
              "condition": "minecraft:location_check",
              "predicate": {
                "biomes": [
                  "minecraft:swamp",
                  "minecraft:mangrove_swamp"
                ]
              }
            }
          ],
          "weight": 7
        },
        {
          "type": "minecraft:loot_table",
          "value": "evercraft:pets/biome/mythical_12",
          "conditions": [
            {
              "condition": "minecraft:location_check",
              "predicate": {
                "biomes": "minecraft:mushroom_fields"
              }
            }
          ],
          "weight": 7
        },
        {
          "type": "minecraft:loot_table",
          "value": "evercraft:pets/biome/mythical_13",
          "conditions": [
            {
              "condition": "minecraft:location_check",
              "predicate": {
                "biomes": [
                  "minecraft:snowy_plains",
                  "minecraft:ice_spikes",
                  "minecraft:snowy_beach"
                ]
              }
            }
          ],
          "weight": 7
        },
        {
          "type": "minecraft:loot_table",
          "value": "evercraft:pets/biome/mythical_14",
          "conditions": [
            {
              "condition": "minecraft:location_check",
              "predicate": {
                "biomes": [
                  "minecraft:badlands",
                  "minecraft:eroded_badlands",
                  "minecraft:wooded_badlands"
                ]
              }
            }
          ],
          "weight": 7
        },
        {
          "type": "minecraft:loot_table",
          "value": "evercraft:pets/biome/mythical_15",
          "conditions": [
            {
              "condition": "minecraft:location_check",
              "predicate": {
                "biomes": "minecraft:lush_caves"
              }
            }
          ],
          "weight": 7
        },
        {
          "type": "minecraft:loot_table",
          "value": "evercraft:pets/biome/mythical_16",
          "conditions": [
            {
              "condition": "minecraft:location_check",
              "predicate": {
                "biomes": "minecraft:dripstone_caves"
              }
            }
          ],
          "weight": 7
        },
        {
          "type": "minecraft:loot_table",
          "value": "evercraft:pets/biome/mythical_17",
          "conditions": [
            {
              "condition": "minecraft:location_check",
              "predicate": {
                "biomes": "minecraft:deep_dark"
              }
            }
          ],
          "weight": 7
        },
        {
          "type": "minecraft:loot_table",
          "value": "evercraft:pets/biome/mythical_18",
          "conditions": [
            {
              "condition": "minecraft:location_check",
              "predicate": {
                "biomes": "minecraft:nether_wastes"
              }
            }
          ],
          "weight": 7
        },
        {
          "type": "minecraft:loot_table",
          "value": "evercraft:pets/biome/mythical_19",
          "conditions": [
            {
              "condition": "minecraft:location_check",
              "predicate": {
                "biomes": "minecraft:crimson_forest"
              }
            }
          ],
          "weight": 7
        },
        {
          "type": "minecraft:loot_table",
          "value": "evercraft:pets/biome/mythical_20",
          "conditions": [
            {
              "condition": "minecraft:location_check",
              "predicate": {
                "biomes": "minecraft:warped_forest"
              }
            }
          ],
          "weight": 7
        },
        {
          "type": "minecraft:loot_table",
          "value": "evercraft:pets/biome/mythical_21",
          "conditions": [
            {
              "condition": "minecraft:location_check",
              "predicate": {
                "biomes": "minecraft:basalt_deltas"
              }
            }
          ],
          "weight": 7
        },
        {
          "type": "minecraft:loot_table",
          "value": "evercraft:pets/biome/mythical_22",
          "conditions": [
            {
              "condition": "minecraft:location_check",
              "predicate": {
                "biomes": "minecraft:soul_sand_valley"
              }
            }
          ],
          "weight": 7
        },
        {
          "type": "minecraft:loot_table",
          "value": "evercraft:pets/biome/mythical_23",
          "conditions": [
            {
              "condition": "minecraft:location_check",
              "predicate": {
                "biomes": [
                  "minecraft:the_end",
                  "minecraft:end_midlands",
                  "minecraft:end_highlands",
                  "minecraft:end_barrens",
                  "minecraft:small_end_islands"
                ]
              }
            }
          ],
          "weight": 7
        }
      ]
    },
    {
      "rolls": 1,
      "comment": "ARTIFACT POOL - 35% chance",
      "entries": [
        {
          "type": "minecraft:empty",
          "weight": 65
        },
        {
          "type": "minecraft:loot_table",
          "value": "evercraft:artifacts/mythical/main",
          "weight": 35
        }
      ]
    },
    {
      "rolls": 1,
      "comment": "CHARM POOL - 12% chance",
      "entries": [
        {
          "type": "minecraft:empty",
          "weight": 88
        },
        {
          "type": "minecraft:loot_table",
          "value": "evercraft:treasure/charms/mythical",
          "weight": 12
        }
      ]
    },
    {
      "rolls": 1,
      "comment": "ENCHANTED BOOK POOL - 3% chance",
      "entries": [
        {
          "type": "minecraft:empty",
          "weight": 97
        },
        {
          "type": "minecraft:item",
          "name": "minecraft:book",
          "weight": 3,
          "functions": [
            {
              "function": "minecraft:enchant_with_levels",
              "levels": 60,
              "options": "#minecraft:on_random_loot"
            }
          ]
        }
      ]
    },
    {
      "rolls": 1,
      "comment": "POTION POOL - 50% chance for structure potions",
      "entries": [
        {
          "type": "minecraft:empty",
          "weight": 50
        },
        {
          "type": "minecraft:loot_table",
          "value": "evercraft:potions/structure/pool_mythical",
          "weight": 50
        }
      ]
    },
    {
      "rolls": 1,
      "comment": "SPAWNER EGG POOL - 5% chance",
      "entries": [
        {
          "type": "minecraft:empty",
          "weight": 95
        },
        {
          "type": "minecraft:loot_table",
          "weight": 5,
          "value": "evercraft:spawners/mob_essence"
        }
      ]
    },
    {
      "rolls": 1,
      "comment": "ARMOR TRIM POOL - Random trim template",
      "entries": [
        {
          "type": "minecraft:empty",
          "weight": 90
        },
        {
          "type": "minecraft:item",
          "name": "minecraft:sentry_armor_trim_smithing_template",
          "weight": 2
        },
        {
          "type": "minecraft:item",
          "name": "minecraft:eye_armor_trim_smithing_template",
          "weight": 2
        },
        {
          "type": "minecraft:item",
          "name": "minecraft:flow_armor_trim_smithing_template",
          "weight": 2
        },
        {
          "type": "minecraft:item",
          "name": "minecraft:bolt_armor_trim_smithing_template",
          "weight": 2
        },
        {
          "type": "minecraft:item",
          "name": "minecraft:netherite_upgrade_smithing_template",
          "weight": 2
        }
      ]
    },
    {
      "rolls": {
        "type": "minecraft:uniform",
        "min": 2,
        "max": 3
      },
      "comment": "BIOME SLOTS - Reserved for biome-specific items",
      "entries": [
        {
          "type": "minecraft:empty",
          "weight": 50
        },
        {
          "type": "minecraft:loot_table",
          "value": "evercraft:treasure/chests/default/biome_items_mythical",
          "weight": 50
        }
      ]
    },
    {
      "rolls": 1,
      "comment": "HORSE ARMOR - Diamond only, luck-gated",
      "entries": [
        {
          "type": "minecraft:empty",
          "weight": 93
        },
        {
          "type": "minecraft:item",
          "name": "minecraft:diamond_horse_armor",
          "weight": 2,
          "conditions": [
            {
              "condition": "minecraft:value_check",
              "value": {
                "type": "minecraft:random",
                "min": 0,
                "max": 100
              },
              "range": {
                "min": 0,
                "max": {
                  "type": "minecraft:score",
                  "target": {
                    "type": "minecraft:fixed",
                    "name": "#luck"
                  },
                  "score": "evercraft.luck"
                }
              }
            }
          ]
        },
        {
          "type": "minecraft:item",
          "name": "minecraft:saddle",
          "weight": 5
        }
      ]
    },
    {
      "rolls": 1,
      "comment": "NAUTILUS ARMOR - Golden/Diamond, luck-gated",
      "entries": [
        {
          "type": "minecraft:empty",
          "weight": 93
        },
        {
          "type": "minecraft:item",
          "name": "minecraft:golden_nautilus_armor",
          "weight": 2,
          "conditions": [
            {
              "condition": "minecraft:value_check",
              "value": {
                "type": "minecraft:random",
                "min": 0,
                "max": 100
              },
              "range": {
                "min": 0,
                "max": {
                  "type": "minecraft:score",
                  "target": {
                    "type": "minecraft:fixed",
                    "name": "#luck"
                  },
                  "score": "evercraft.luck"
                }
              }
            }
          ]
        },
        {
          "type": "minecraft:item",
          "name": "minecraft:diamond_nautilus_armor",
          "weight": 2,
          "conditions": [
            {
              "condition": "minecraft:value_check",
              "value": {
                "type": "minecraft:random",
                "min": 0,
                "max": 100
              },
              "range": {
                "min": 0,
                "max": {
                  "type": "minecraft:score",
                  "target": {
                    "type": "minecraft:fixed",
                    "name": "#luck"
                  },
                  "score": "evercraft.luck"
                }
              }
            }
          ]
        },
        {
          "type": "minecraft:item",
          "name": "minecraft:saddle",
          "weight": 3
        }
      ]
    },
    {
      "rolls": 1,
      "comment": "COMPANION TREAT POOL - 3% chance",
      "entries": [
        {
          "type": "minecraft:empty",
          "weight": 97
        },
        {
          "type": "minecraft:loot_table",
          "value": "evercraft:companions/items/pet_treat",
          "weight": 3
        }
      ]
    },
    {
      "rolls": 1,
      "comment": "LUCK BONUS ROLLS",
      "entries": [
        {
          "type": "minecraft:loot_table",
          "value": "evercraft:treasure/luck/bonus_rolls"
        }
      ]
    },
    {
      "rolls": 1,
      "comment": "Crystal of Dreams (3% chance)",
      "entries": [
        {
          "type": "minecraft:empty",
          "weight": 97
        },
        {
          "type": "minecraft:loot_table",
          "value": "evercraft:items/crystal_of_dreams",
          "weight": 3
        }
      ]
    },
    {
      "rolls": 1,
      "comment": "B5 BALANCE: 3% chance for bonus totem (Mythical only)",
      "entries": [
        {
          "type": "minecraft:empty",
          "weight": 97
        },
        {
          "type": "minecraft:item",
          "name": "minecraft:totem_of_undying",
          "weight": 3
        }
      ]
    },
    {
      "rolls": 1,
      "comment": "AWAKENING STONE - 20% chance",
      "entries": [
        {
          "type": "minecraft:empty",
          "weight": 80
        },
        {
          "type": "minecraft:loot_table",
          "value": "evercraft:weapon_mastery/stones/mythical_stone",
          "weight": 20
        }
      ]
    },
    {
      "rolls": 1,
      "comment": "DREAM AEGIS - 0.01% chance",
      "entries": [
        {
          "type": "minecraft:empty",
          "weight": 9999
        },
        {
          "type": "minecraft:loot_table",
          "value": "evercraft:artifacts/mythical/dream_aegis",
          "weight": 1
        }
      ]
    },
    {
      "rolls": 1,
      "comment": "RING POOL - 1% chance (ring_void)",
      "entries": [
        {
          "type": "minecraft:empty",
          "weight": 99
        },
        {
          "type": "minecraft:loot_table",
          "value": "evercraft:artifacts/special/ring_void",
          "weight": 1
        }
      ]
    },
    {
      "rolls": 1,
      "comment": "DUNGEON KEY - 7% chance",
      "entries": [
        {
          "type": "minecraft:empty",
          "weight": 93
        },
        {
          "type": "minecraft:loot_table",
          "value": "evercraft:dungeon/key",
          "weight": 7
        }
      ]
    },
    {
      "rolls": 1,
      "comment": "SATCHEL POOL - 2% chance",
      "entries": [
        {
          "type": "minecraft:empty",
          "weight": 98
        },
        {
          "type": "minecraft:loot_table",
          "value": "evercraft:satchel/mythical",
          "weight": 2
        }
      ]
    },
    {
      "rolls": 1,
      "comment": "PET CRATE - 0.5% chance",
      "entries": [
        {
          "type": "minecraft:empty",
          "weight": 199
        },
        {
          "type": "minecraft:loot_table",
          "value": "evercraft:crates/items/pet_mythical",
          "weight": 1
        }
      ]
    },
    {
      "rolls": 1,
      "comment": "ARTIFACT CRATE - 0.5% chance",
      "entries": [
        {
          "type": "minecraft:empty",
          "weight": 199
        },
        {
          "type": "minecraft:loot_table",
          "value": "evercraft:crates/items/artifact_mythical",
          "weight": 1
        }
      ]
    },
    {
      "rolls": 1,
      "comment": "GUIDESTONE - 3% chance",
      "entries": [
        {
          "type": "minecraft:empty",
          "weight": 97
        },
        {
          "type": "minecraft:loot_table",
          "value": "evercraft:guidestone/guidestone_drop",
          "weight": 3
        }
      ]
    },
    {
      "rolls": 1,
      "comment": "HEART OF THE SEA - 2% chance",
      "entries": [
        {
          "type": "minecraft:empty",
          "weight": 98
        },
        {
          "type": "minecraft:item",
          "name": "minecraft:heart_of_the_sea",
          "weight": 2
        }
      ]
    }
  ]
}
